{
  "build": {
    "development": {
      "developmentClient": true,
      "distribution": "internal",
      "env": {
        "APP_VARIANT": "dev"
      },
      "autoIncrement": true
    },
    "development-sim": {
      "ios": {
        "simulator": true
      }
    },
    "preview": {
      "distribution": "internal",
      "autoIncrement": true
    },
    "production": {
      "autoIncrement": true
    }
  },
  "cli": {
    "appVersionSource": "remote"
  },
  "submit": {
    "production": {
      "ios": {
        "ascAppId": "6755954909",
        "appleTeamId": "3876B748Z2"
      }
    }
  }
}
